SeleniumTwo/__init__.py
SeleniumTwo/cli.py
SeleniumTwo/find_elements.py
SeleniumTwo/get_driver.py
SeleniumTwo/invoke_api.py
SeleniumTwo/system.py
seleniumtwo-0.3.4.dist-info/METADATA
seleniumtwo-0.3.4.dist-info/WHEEL
seleniumtwo-0.3.4.dist-info/entry_points.txt
seleniumtwo-0.3.4.dist-info/top_level.txt
seleniumtwo-0.3.4.dist-info/RECORD
